linkup/__init__.py
linkup/_client.py
linkup/_errors.py
linkup/_types.py
linkup/_version.py
linkup/py.typed
linkup_sdk-0.9.1.dist-info/METADATA
linkup_sdk-0.9.1.dist-info/WHEEL
linkup_sdk-0.9.1.dist-info/licenses/LICENSE
linkup_sdk-0.9.1.dist-info/RECORD
