Metadata-Version: 2.4
Name: linkup-sdk
Version: 0.9.1
Summary: A Python Client SDK for the Linkup API
Project-URL: Documentation, https://github.com/LinkupPlatform/linkup-python-sdk#readme
Project-URL: Homepage, https://github.com/LinkupPlatform/linkup-python-sdk
Project-URL: Source, https://github.com/LinkupPlatform/linkup-python-sdk
Project-URL: Tracker, https://github.com/LinkupPlatform/linkup-python-sdk/issues
Author-email: LINKUP TECHNOLOGIES <contact@linkup.so>
License-Expression: MIT
License-File: LICENSE
Keywords: api,client,linkup,sdk,search
Classifier: Intended Audience :: Developers
Classifier: License :: OSI Approved :: MIT License
Classifier: Operating System :: OS Independent
Classifier: Topic :: Software Development :: Libraries :: Python Modules
Requires-Python: >=3.9
Requires-Dist: httpx>=0.23.0
Requires-Dist: pydantic>=2.0.0
Provides-Extra: build
Requires-Dist: uv<0.9.0,>=0.8.0; extra == 'build'
